<annotation>
    <filename>CHESS_OFFICE_S_B_frame_1319_jpg.rf.c90cbf56d239897437d153b0c05d6833.jpg</filename>
    <imagesize>
        <width>384</width>
        <height>216</height>
    </imagesize>
    <object>
        <bndbox>
            <xmin>21</xmin>
            <ymin>190</ymin>
            <xmax>94</xmax>
            <ymax>26</ymax>
        </bndbox>
    </object>
    <object>
        <bndbox>
            <xmin>219</xmin>
            <ymin>208</ymin>
            <xmax>57</xmax>
            <ymax>8</ymax>
        </bndbox>
    </object>
    <object>
        <bndbox>
            <xmin>206</xmin>
            <ymin>0</ymin>
            <xmax>56</xmax>
            <ymax>33</ymax>
        </bndbox>
    </object>
    <object>
        <bndbox>
            <xmin>73</xmin>
            <ymin>1</ymin>
            <xmax>62</xmax>
            <ymax>26</ymax>
        </bndbox>
    </object>
</annotation>
