<annotation>
    <filename>JENGA_COURTYARD_H_B_frame_0696_jpg.rf.0af88162d25995b12b70cee7f6374741.jpg</filename>
    <imagesize>
        <width>384</width>
        <height>216</height>
    </imagesize>
    <object>
        <bndbox>
            <xmin>195</xmin>
            <ymin>88</ymin>
            <xmax>97</xmax>
            <ymax>127</ymax>
        </bndbox>
    </object>
    <object>
        <bndbox>
            <xmin>209</xmin>
            <ymin>95</ymin>
            <xmax>33</xmax>
            <ymax>29</ymax>
        </bndbox>
    </object>
    <object>
        <bndbox>
            <xmin>125</xmin>
            <ymin>98</ymin>
            <xmax>23</xmax>
            <ymax>39</ymax>
        </bndbox>
    </object>
</annotation>
