<annotation>
    <filename>JENGA_OFFICE_B_S_frame_1369_jpg.rf.7cb962f64c5436742da5732c9b3207b1.jpg</filename>
    <imagesize>
        <width>384</width>
        <height>216</height>
    </imagesize>
    <object>
        <bndbox>
            <xmin>35</xmin>
            <ymin>56</ymin>
            <xmax>54</xmax>
            <ymax>113</ymax>
        </bndbox>
    </object>
    <object>
        <bndbox>
            <xmin>133</xmin>
            <ymin>123</ymin>
            <xmax>91</xmax>
            <ymax>92</ymax>
        </bndbox>
    </object>
    <object>
        <bndbox>
            <xmin>196</xmin>
            <ymin>36</ymin>
            <xmax>52</xmax>
            <ymax>54</ymax>
        </bndbox>
    </object>
    <object>
        <bndbox>
            <xmin>81</xmin>
            <ymin>38</ymin>
            <xmax>46</xmax>
            <ymax>65</ymax>
        </bndbox>
    </object>
</annotation>
