<annotation>
    <filename>PUZZLE_OFFICE_T_S_frame_2187_jpg.rf.d534d0baac3a05d31f031f405d0a1ee4.jpg</filename>
    <imagesize>
        <width>384</width>
        <height>216</height>
    </imagesize>
    <object>
        <bndbox>
            <xmin>56</xmin>
            <ymin>136</ymin>
            <xmax>77</xmax>
            <ymax>67</ymax>
        </bndbox>
    </object>
    <object>
        <bndbox>
            <xmin>169</xmin>
            <ymin>120</ymin>
            <xmax>51</xmax>
            <ymax>58</ymax>
        </bndbox>
    </object>
    <object>
        <bndbox>
            <xmin>136</xmin>
            <ymin>64</ymin>
            <xmax>43</xmax>
            <ymax>40</ymax>
        </bndbox>
    </object>
    <object>
        <bndbox>
            <xmin>51</xmin>
            <ymin>65</ymin>
            <xmax>69</xmax>
            <ymax>56</ymax>
        </bndbox>
    </object>
</annotation>
