<annotation>
    <filename>PUZZLE_LIVINGROOM_S_H_frame_0196_jpg.rf.9a8697f8455da4a51755b1346f4107f0.jpg</filename>
    <imagesize>
        <width>384</width>
        <height>216</height>
    </imagesize>
    <object>
        <bndbox>
            <xmin>7</xmin>
            <ymin>151</ymin>
            <xmax>110</xmax>
            <ymax>63</ymax>
        </bndbox>
    </object>
    <object>
        <bndbox>
            <xmin>202</xmin>
            <ymin>115</ymin>
            <xmax>58</xmax>
            <ymax>45</ymax>
        </bndbox>
    </object>
    <object>
        <bndbox>
            <xmin>300</xmin>
            <ymin>122</ymin>
            <xmax>64</xmax>
            <ymax>83</ymax>
        </bndbox>
    </object>
    <object>
        <bndbox>
            <xmin>167</xmin>
            <ymin>85</ymin>
            <xmax>42</xmax>
            <ymax>46</ymax>
        </bndbox>
    </object>
</annotation>
