<annotation>
    <filename>CARDS_LIVINGROOM_B_T_frame_2269_jpg.rf.b0ec43e51ca485efd990406a7cc64e40.jpg</filename>
    <object>
        <bndbox>
            <xmin>180</xmin>
            <ymin>677</ymin>
            <xmax>83</xmax>
            <ymax>42</ymax>
        </bndbox>
    </object>
    <object>
        <bndbox>
            <xmin>653</xmin>
            <ymin>704</ymin>
            <xmax>76</xmax>
            <ymax>15</ymax>
        </bndbox>
    </object>
    <object>
        <bndbox>
            <xmin>746</xmin>
            <ymin>329</ymin>
            <xmax>271</xmax>
            <ymax>127</ymax>
        </bndbox>
    </object>
    <object>
        <bndbox>
            <xmin>551</xmin>
            <ymin>300</ymin>
            <xmax>195</xmax>
            <ymax>131</ymax>
        </bndbox>
    </object>
</annotation>
