<annotation>
    <filename>CARDS_LIVINGROOM_B_T_frame_2405_jpg.rf.523d1b108b64c83f7463d809aad6666e.jpg</filename>
    <object>
        <bndbox>
            <xmin>176</xmin>
            <ymin>673</ymin>
            <xmax>91</xmax>
            <ymax>46</ymax>
        </bndbox>
    </object>
    <object>
        <bndbox>
            <xmin>653</xmin>
            <ymin>609</ymin>
            <xmax>186</xmax>
            <ymax>110</ymax>
        </bndbox>
    </object>
    <object>
        <bndbox>
            <xmin>720</xmin>
            <ymin>297</ymin>
            <xmax>257</xmax>
            <ymax>128</ymax>
        </bndbox>
    </object>
    <object>
        <bndbox>
            <xmin>526</xmin>
            <ymin>285</ymin>
            <xmax>194</xmax>
            <ymax>146</ymax>
        </bndbox>
    </object>
</annotation>
