<annotation>
    <filename>CHESS_LIVINGROOM_T_H_frame_1251_jpg.rf.d860a77ea6d4ee70b83ce284113c662d.jpg</filename>
    <object>
        <bndbox>
            <xmin>1</xmin>
            <ymin>143</ymin>
            <xmax>122</xmax>
            <ymax>246</ymax>
        </bndbox>
    </object>
    <object>
        <bndbox>
            <xmin>521</xmin>
            <ymin>219</ymin>
            <xmax>293</xmax>
            <ymax>235</ymax>
        </bndbox>
    </object>
    <object>
        <bndbox>
            <xmin>679</xmin>
            <ymin>384</ymin>
            <xmax>135</xmax>
            <ymax>154</ymax>
        </bndbox>
    </object>
</annotation>
