<annotation>
    <filename>PUZZLE_COURTYARD_S_B_frame_1807_jpg.rf.02ef1df7c289b887f964080c111f7aa4.jpg</filename>
    <object>
        <bndbox>
            <xmin>701</xmin>
            <ymin>603</ymin>
            <xmax>289</xmax>
            <ymax>116</ymax>
        </bndbox>
    </object>
    <object>
        <bndbox>
            <xmin>561</xmin>
            <ymin>304</ymin>
            <xmax>195</xmax>
            <ymax>187</ymax>
        </bndbox>
    </object>
    <object>
        <bndbox>
            <xmin>31</xmin>
            <ymin>358</ymin>
            <xmax>272</xmax>
            <ymax>359</ymax>
        </bndbox>
    </object>
</annotation>
