<annotation>
	<folder></folder>
	<filename>CARDS_OFFICE_S_B_frame_0985_jpg.rf.bdedb49e708ad5f885da5f16e2d45d2a.jpg</filename>
	<path>CARDS_OFFICE_S_B_frame_0985_jpg.rf.bdedb49e708ad5f885da5f16e2d45d2a.jpg</path>
	<source>
		<database>roboflow.ai</database>
	</source>
	<size>
		<width>1280</width>
		<height>720</height>
		<depth>3</depth>
	</size>
	<segmented>0</segmented>
	<object>
		<name>yourleft</name>
		<pose>Unspecified</pose>
		<truncated>0</truncated>
		<difficult>0</difficult>
		<occluded>0</occluded>
		<bndbox>
			<xmin>638</xmin>
			<xmax>768</xmax>
			<ymin>240</ymin>
			<ymax>370</ymax>
		</bndbox>
	</object>
	<object>
		<name>yourright</name>
		<pose>Unspecified</pose>
		<truncated>0</truncated>
		<difficult>0</difficult>
		<occluded>0</occluded>
		<bndbox>
			<xmin>482</xmin>
			<xmax>597</xmax>
			<ymin>253</ymin>
			<ymax>360</ymax>
		</bndbox>
	</object>
</annotation>
