<annotation>
	<folder></folder>
	<filename>CHESS_COURTYARD_T_B_frame_0179_jpg.rf.755fd00e18902f534dd6660aa6771e1c.jpg</filename>
	<path>CHESS_COURTYARD_T_B_frame_0179_jpg.rf.755fd00e18902f534dd6660aa6771e1c.jpg</path>
	<source>
		<database>roboflow.ai</database>
	</source>
	<size>
		<width>1280</width>
		<height>720</height>
		<depth>3</depth>
	</size>
	<segmented>0</segmented>
	<object>
		<name>yourleft</name>
		<pose>Unspecified</pose>
		<truncated>0</truncated>
		<difficult>0</difficult>
		<occluded>0</occluded>
		<bndbox>
			<xmin>731</xmin>
			<xmax>875</xmax>
			<ymin>298</ymin>
			<ymax>414</ymax>
		</bndbox>
	</object>
	<object>
		<name>yourright</name>
		<pose>Unspecified</pose>
		<truncated>0</truncated>
		<difficult>0</difficult>
		<occluded>0</occluded>
		<bndbox>
			<xmin>473</xmin>
			<xmax>640</xmax>
			<ymin>260</ymin>
			<ymax>368</ymax>
		</bndbox>
	</object>
</annotation>
