<annotation>
	<folder></folder>
	<filename>CHESS_OFFICE_B_S_frame_1906_jpg.rf.de9f81c27f9fe6d1e9c039c4eea4262c.jpg</filename>
	<path>CHESS_OFFICE_B_S_frame_1906_jpg.rf.de9f81c27f9fe6d1e9c039c4eea4262c.jpg</path>
	<source>
		<database>roboflow.ai</database>
	</source>
	<size>
		<width>1280</width>
		<height>720</height>
		<depth>3</depth>
	</size>
	<segmented>0</segmented>
	<object>
		<name>yourleft</name>
		<pose>Unspecified</pose>
		<truncated>0</truncated>
		<difficult>0</difficult>
		<occluded>0</occluded>
		<bndbox>
			<xmin>622</xmin>
			<xmax>788</xmax>
			<ymin>223</ymin>
			<ymax>351</ymax>
		</bndbox>
	</object>
	<object>
		<name>yourright</name>
		<pose>Unspecified</pose>
		<truncated>0</truncated>
		<difficult>0</difficult>
		<occluded>0</occluded>
		<bndbox>
			<xmin>456</xmin>
			<xmax>616</xmax>
			<ymin>217</ymin>
			<ymax>365</ymax>
		</bndbox>
	</object>
	<object>
		<name>myright</name>
		<pose>Unspecified</pose>
		<truncated>0</truncated>
		<difficult>0</difficult>
		<occluded>0</occluded>
		<bndbox>
			<xmin>664</xmin>
			<xmax>847</xmax>
			<ymin>688</ymin>
			<ymax>720</ymax>
		</bndbox>
	</object>
</annotation>
