<annotation>
	<folder></folder>
	<filename>CHESS_OFFICE_T_H_frame_1499_jpg.rf.350c0131041862cffccfdac03456d72c.jpg</filename>
	<path>CHESS_OFFICE_T_H_frame_1499_jpg.rf.350c0131041862cffccfdac03456d72c.jpg</path>
	<source>
		<database>roboflow.ai</database>
	</source>
	<size>
		<width>1280</width>
		<height>720</height>
		<depth>3</depth>
	</size>
	<segmented>0</segmented>
	<object>
		<name>myleft</name>
		<pose>Unspecified</pose>
		<truncated>0</truncated>
		<difficult>0</difficult>
		<occluded>0</occluded>
		<bndbox>
			<xmin>186</xmin>
			<xmax>387</xmax>
			<ymin>664</ymin>
			<ymax>718</ymax>
		</bndbox>
	</object>
	<object>
		<name>myright</name>
		<pose>Unspecified</pose>
		<truncated>0</truncated>
		<difficult>0</difficult>
		<occluded>0</occluded>
		<bndbox>
			<xmin>395</xmin>
			<xmax>592</xmax>
			<ymin>635</ymin>
			<ymax>719</ymax>
		</bndbox>
	</object>
	<object>
		<name>yourleft</name>
		<pose>Unspecified</pose>
		<truncated>0</truncated>
		<difficult>0</difficult>
		<occluded>0</occluded>
		<bndbox>
			<xmin>577</xmin>
			<xmax>710</xmax>
			<ymin>160</ymin>
			<ymax>246</ymax>
		</bndbox>
	</object>
	<object>
		<name>yourright</name>
		<pose>Unspecified</pose>
		<truncated>0</truncated>
		<difficult>0</difficult>
		<occluded>0</occluded>
		<bndbox>
			<xmin>349</xmin>
			<xmax>515</xmax>
			<ymin>100</ymin>
			<ymax>269</ymax>
		</bndbox>
	</object>
</annotation>
